<?xml version="1.0" encoding="UTF-8"?>
<!DOCTYPE suite SYSTEM "http://testng.org/testng-1.0.dtd">
<suite name="Samsung API Test Suite">



    <test name="Sign In">
        <classes>
            <class name="te.application.api.test.B2B.sck.positive.SignInTestSck" />
        </classes>
    </test>



    <listeners>
        <listener class-name="te.application.listener.extentReportListener" />
        <listener class-name="te.application.Analyzer.AnnotationTransformer" />
    </listeners>
</suite>